opentelemetry/instrumentation/crewai/__init__.py
opentelemetry/instrumentation/crewai/instrumentation.py
opentelemetry/instrumentation/crewai/version.py
splunk_otel_instrumentation_crewai-0.1.2.dist-info/METADATA
splunk_otel_instrumentation_crewai-0.1.2.dist-info/WHEEL
splunk_otel_instrumentation_crewai-0.1.2.dist-info/entry_points.txt
splunk_otel_instrumentation_crewai-0.1.2.dist-info/RECORD
